django_feedback_govuk/__init__.py
django_feedback_govuk/admin.py
django_feedback_govuk/apps.py
django_feedback_govuk/forms.py
django_feedback_govuk/migrations/0001_initial.py
django_feedback_govuk/migrations/0002_alter_feedback_submitter.py
django_feedback_govuk/migrations/0003_restructure_feedback.py
django_feedback_govuk/migrations/0004_alter_basefeedback_id.py
django_feedback_govuk/migrations/__init__.py
django_feedback_govuk/models.py
django_feedback_govuk/settings.py
django_feedback_govuk/static/django_feedback_govuk/star-rating.css
django_feedback_govuk/templates/django_feedback_govuk/includes/pagination.html
django_feedback_govuk/templates/django_feedback_govuk/partials/confirm.html
django_feedback_govuk/templates/django_feedback_govuk/partials/listing.html
django_feedback_govuk/templates/django_feedback_govuk/partials/submit.html
django_feedback_govuk/templates/django_feedback_govuk/partials/submitted.html
django_feedback_govuk/templates/django_feedback_govuk/templates/confirm.html
django_feedback_govuk/templates/django_feedback_govuk/templates/listing.html
django_feedback_govuk/templates/django_feedback_govuk/templates/submit.html
django_feedback_govuk/templates/django_feedback_govuk/templates/submitted.html
django_feedback_govuk/templates/django_feedback_govuk/widgets/star_rating/radios.html
django_feedback_govuk/templates/django_feedback_govuk/widgets/star_rating/star_rating.html
django_feedback_govuk/templatetags/__init__.py
django_feedback_govuk/templatetags/feedback_tags.py
django_feedback_govuk/tests/__init__.py
django_feedback_govuk/tests/factories.py
django_feedback_govuk/tests/settings.py
django_feedback_govuk/tests/test_views.py
django_feedback_govuk/tests/urls.py
django_feedback_govuk/urls.py
django_feedback_govuk/views.py
django_feedback_govuk-0.2.12.dist-info/LICENSE
django_feedback_govuk-0.2.12.dist-info/METADATA
django_feedback_govuk-0.2.12.dist-info/WHEEL
django_feedback_govuk-0.2.12.dist-info/RECORD
