Metadata-Version: 2.3
Name: django-feedback-govuk
Version: 0.2.12
Summary: A Django app to gather and send internal Government staff feedback
License: MIT
Author: jafacakes2011
Author-email: cameron.lamb@digitial.trade.gov.uk
Requires-Python: >=3.9,<4.0
Classifier: Development Status :: 4 - Beta
Classifier: Environment :: Web Environment
Classifier: Intended Audience :: Developers
Classifier: License :: OSI Approved :: MIT License
Classifier: Operating System :: OS Independent
Classifier: Programming Language :: Python :: 3
Classifier: Programming Language :: Python :: 3.9
Classifier: Programming Language :: Python :: 3.10
Classifier: Programming Language :: Python :: 3.11
Classifier: Programming Language :: Python :: 3.12
Classifier: Programming Language :: Python :: 3.13
Classifier: Programming Language :: Python :: 3 :: Only
Classifier: Programming Language :: Python :: Implementation :: CPython
Classifier: Topic :: Software Development :: Libraries :: Application Frameworks
Classifier: Topic :: Software Development :: Libraries :: Python Modules
Requires-Dist: Django (>=4.2,<6.0)
Requires-Dist: crispy-forms-gds (>=0.2.4,<0.3.0)
Requires-Dist: django-crispy-forms (>=1.9,<2.0)
